Xdi8Translator/__init__.py
Xdi8Translator/data.py
Xdi8Translator/translator.py
Xdi8Translator-0.4.0.dist-info/METADATA
Xdi8Translator-0.4.0.dist-info/WHEEL
Xdi8Translator-0.4.0.dist-info/top_level.txt
Xdi8Translator-0.4.0.dist-info/RECORD
