Metadata-Version: 2.1
Name: Xdi8Translator
Version: 0.4.0
Summary: Multiway Xdi8 Translator
Home-page: https://github.com/edward-martyr/Xdi8Translator
Author: Edward Martyr
Author-email: edwardmartyr@outlook.com
License: MIT
Platform: UNKNOWN
Requires-Dist: jieba
